cmsdk/__init__.py
cmsdk/core/__init__.py
cmsdk/core/base_view.py
cmsdk/core/jsonapp.py
cmsdk/errors/__init__.py
cmsdk/errors/exceptions.py
cmsdk/types/__init__.py
cmsdk/types/models.py
cmsdk/utils/__init__.py
cmsdk/utils/file_formats.py
cmsdk/utils/validators.py
cmsdk/views/__init__.py
cmsdk/views/action_grid_view.py
cmsdk/views/action_list_view.py
cmsdk/views/base_action_view.py
cmsdk/views/card_view.py
cmsdk/views/carousel_view.py
cmsdk/views/form_view.py
cmsdk/views/map_view.py
cmsdk/views/media_view.py
cmsdk/views/message_view.py
cmsdk/views/qr_display_view.py
cmsdk/views/qr_scan_view.py
cmsdk/views/reader_view.py
cmsdk/views/timeline_view.py
cmsdk-1.0.1.dist-info/METADATA
cmsdk-1.0.1.dist-info/WHEEL
cmsdk-1.0.1.dist-info/top_level.txt
cmsdk-1.0.1.dist-info/RECORD
