Metadata-Version: 2.4
Name: cmsdk
Version: 1.0.1
Summary: A modern Python SDK for generating dynamic JSON interfaces
Author: JsonApp Team
License: MIT
Keywords: json,interface,form-builder,sdk,dynamic-ui,mobile-apps
Classifier: Development Status :: 4 - Beta
Classifier: Intended Audience :: Developers
Classifier: License :: OSI Approved :: MIT License
Classifier: Programming Language :: Python :: 3
Classifier: Programming Language :: Python :: 3.10
Classifier: Programming Language :: Python :: 3.11
Classifier: Programming Language :: Python :: 3.12
Requires-Python: >=3.10
Requires-Dist: cryptography>=41.0.0
Requires-Dist: markdown>=3.4.0
Requires-Dist: bleach>=6.0.0
Provides-Extra: dev
Requires-Dist: pytest>=7.4.0; extra == "dev"
Requires-Dist: pytest-cov>=4.1.0; extra == "dev"
Requires-Dist: black>=23.0.0; extra == "dev"
Requires-Dist: mypy>=1.5.0; extra == "dev"
Requires-Dist: ruff>=0.0.280; extra == "dev"
